MANIFEST.in
README.md
setup.py
albert_pytorch/__init__.py
albert_pytorch/__init__.pyc
albert_pytorch/plus.py
albert_pytorch/pre_classifier.py
albert_pytorch/pre_classifier.pyc
albert_pytorch/pre_mask.py
albert_pytorch/utils.py
albert_pytorch.egg-info/PKG-INFO
albert_pytorch.egg-info/SOURCES.txt
albert_pytorch.egg-info/dependency_links.txt
albert_pytorch.egg-info/requires.txt
albert_pytorch.egg-info/top_level.txt
albert_pytorch/callback/__init__.py
albert_pytorch/callback/modelcheckpoint.py
albert_pytorch/callback/optimizater.py
albert_pytorch/callback/progressbar.py
albert_pytorch/callback/utils.py
albert_pytorch/metrics/__init__.py
albert_pytorch/metrics/custom_metrics.py
albert_pytorch/metrics/glue_compute_metrics.py
albert_pytorch/model/__init__.py
albert_pytorch/model/configuration_bert.py
albert_pytorch/model/configuration_utils.py
albert_pytorch/model/file_utils.py
albert_pytorch/model/modeling_albert.py
albert_pytorch/model/modeling_utils.py
albert_pytorch/model/optimization.py
albert_pytorch/model/tokenization_bert.py
albert_pytorch/model/tokenization_utils.py
albert_pytorch/processors/__init__.py
albert_pytorch/processors/glue.py
albert_pytorch/processors/utils.py
albert_pytorch/tools/__init__.py
albert_pytorch/tools/common.py