Metadata-Version: 2.1
Name: albert-pytorch
Version: 0.0.1.9
Summary: albert_pytorch
Home-page: https://github.com/napoler/albert_pytorch
Author: Terry Chan
Author-email: napoler2008@gmail.com
License: UNKNOWN
Platform: UNKNOWN
